README.rst
setup.py
jsonxdm/__init__.py
jsonxdm/jsonxdm.py
jsonxdm.egg-info/PKG-INFO
jsonxdm.egg-info/SOURCES.txt
jsonxdm.egg-info/dependency_links.txt
jsonxdm.egg-info/requires.txt
jsonxdm.egg-info/top_level.txt